cli/__init__.py
cli/cli.py
currency_converter/__init__.py
currency_converter/main.py
currency_converter_ext-0.1.0.dist-info/LICENSE
currency_converter_ext-0.1.0.dist-info/METADATA
currency_converter_ext-0.1.0.dist-info/WHEEL
currency_converter_ext-0.1.0.dist-info/entry_points.txt
currency_converter_ext-0.1.0.dist-info/top_level.txt
currency_converter_ext-0.1.0.dist-info/RECORD
