Metadata-Version: 2.1
Name: currency-converter-ext
Version: 0.1.0
Summary: A comprehensive currency conversion library with CLI
Home-page: https://github.com/yourusername/currency-converter
Author: Your Name
Author-email: your.email@example.com
Keywords: currency converter exchange rates
Classifier: Development Status :: 3 - Alpha
Classifier: Intended Audience :: Developers
Classifier: License :: OSI Approved :: MIT License
Classifier: Operating System :: OS Independent
Classifier: Programming Language :: Python :: 3
Classifier: Programming Language :: Python :: 3.7
Classifier: Programming Language :: Python :: 3.8
Classifier: Programming Language :: Python :: 3.9
Classifier: Programming Language :: Python :: 3.10
Requires-Python: >=3.7
License-File: LICENSE
Requires-Dist: requests
